beaverlog/__init__.py
beaverlog/core.py
beaverlog/themes.py
beaverlog-0.1.0.dist-info/licenses/LICENSE
beaverlog-0.1.0.dist-info/METADATA
beaverlog-0.1.0.dist-info/WHEEL
beaverlog-0.1.0.dist-info/top_level.txt
beaverlog-0.1.0.dist-info/RECORD
