Metadata-Version: 2.4
Name: beaverlog
Version: 0.1.0
Summary: A enhanced python logger
Author-email: Decaux Clément <decauxclement1@gmail.com>
License: MIT
Project-URL: Homepage, https://github.com/ClementDecaux/BeaverLog
Requires-Python: >=3.7
License-File: LICENSE
Dynamic: license-file
